etidel_python/__init__.py
etidel_python/sender.py
etidel_python-0.1.0.dist-info/LICENSE
etidel_python-0.1.0.dist-info/METADATA
etidel_python-0.1.0.dist-info/WHEEL
etidel_python-0.1.0.dist-info/top_level.txt
etidel_python-0.1.0.dist-info/RECORD
